AUTHORS
LICENSE
MANIFEST.in
README.md
relogger_example.cfg
setup.py
bin/.DS_Store
bin/relogger
relogger/__init__.py
relogger/config_parser.py
relogger/relogger.py
relogger/syslog.py
relogger.egg-info/PKG-INFO
relogger.egg-info/SOURCES.txt
relogger.egg-info/dependency_links.txt
relogger.egg-info/top_level.txt